Metadata-Version: 2.1
Name: ednevnik
Version: 0.0.5
Summary: A very basic E-Dnevnik API.
Home-page: UNKNOWN
Author: Parzival
License: MIT
Keywords: ednevnik
Platform: UNKNOWN
Classifier: Development Status :: 5 - Production/Stable
Classifier: Intended Audience :: Education
Classifier: Operating System :: Microsoft :: Windows :: Windows 10
Classifier: License :: OSI Approved :: MIT License
Classifier: Programming Language :: Python :: 3
